{
    "code": "200",
    "data": {
        "c_people_rid": "98D34B00-352C-09B5-A3641841B96CA29E",
        "i_people_type": 1,
        "v_people_first_name": "Yoda",
        "v_people_last_name": "Real",
        "v_people_email": "abc@gmail.com",
        "v_people_passport": "GB8883822",
        "i_people_nationality": "1001",
        "v_people_nationalid": "GB8883821",
        "v_mobile_no": "999999999",
        "v_mobile1_no": "254799666887",
        "v_mobile2_no": "254799666998",
        "v_address": "D-6-13 perumahan atm jalan uthant",
        "v_city": "kampung pandan",
        "v_postal": "55100",
        "v_county": "Kuala Lumpur",
        "v_district": "Kuala Lumpur",
        "i_country": 0,
        "v_email": "abc1@gmail.com",
        "d_dob": "1996-01-01T00:00:00.000+00:00",
        "i_age": 24,
        "i_gander": 0,
        "v_nok_first_name": "John",
        "v_nok_last_name": "Nancy",
        "v_nok_mobile": "+254799456111",
        "v_nok_mobile1": "+254799456222",
        "v_nok_email": "nacy@yahoo.com",
        "v_company_name": "company",
        "v_companypic_first_name": "googg",
        "v_companypic_last_name": "32323",
        "v_company_mobile": "254799456444",
        "v_company_mobile1": "254799456455",
        "v_company_email": "company@gmail.com"
    },
    "message": "OK",
    "timestamp": "1633356648981"
}